directory_treemap/__init__.py
directory_treemap/cli.py
directory_treemap/directory_treemap.py
directory_treemap/utils/__init__.py
directory_treemap/utils/file_utils.py
dirtreemap-0.1.0.dist-info/licenses/LICENSE
dirtreemap-0.1.0.dist-info/METADATA
dirtreemap-0.1.0.dist-info/WHEEL
dirtreemap-0.1.0.dist-info/entry_points.txt
dirtreemap-0.1.0.dist-info/top_level.txt
dirtreemap-0.1.0.dist-info/RECORD
