Metadata-Version: 2.4
Name: dirtreemap
Version: 0.1.0
Summary: Directory treemap visualization tool using Plotly
Author: Greg Elphick
License: MIT License
Project-URL: Homepage, https://github.com/elphick/dirtreemap
Project-URL: Repository, https://github.com/elphick/dirtreemap
Project-URL: Issues, https://github.com/elphick/dirtreemap/issues
Classifier: Programming Language :: Python :: 3
Classifier: License :: OSI Approved :: MIT License
Classifier: Operating System :: OS Independent
Classifier: Topic :: Software Development :: Libraries
Classifier: Topic :: Utilities
Classifier: Intended Audience :: Developers
Classifier: Intended Audience :: Science/Research
Classifier: Development Status :: 3 - Alpha
Requires-Python: >=3.8
License-File: LICENSE
Requires-Dist: plotly
Requires-Dist: pandas
Requires-Dist: tqdm>=4.67.1
Dynamic: license-file
